run_in_subdirectory/__init__.py
run_in_subdirectory/__main__.py
run_in_subdirectory/run_in_subdirectory.py
run_in_subdirectory-1.0.1.dist-info/LICENSE
run_in_subdirectory-1.0.1.dist-info/METADATA
run_in_subdirectory-1.0.1.dist-info/NOTICE
run_in_subdirectory-1.0.1.dist-info/WHEEL
run_in_subdirectory-1.0.1.dist-info/entry_points.txt
run_in_subdirectory-1.0.1.dist-info/RECORD
