Metadata-Version: 2.1
Name: run-in-subdirectory
Version: 1.0.1
Summary: A command-line utility for running commands in subdirectories (e.g. in a monorepo) with a set of pre-commit hooks
Home-page: https://github.com/egormkn/run-in-subdirectory
License: MIT
Keywords: git,hooks,utilities,pre-commit,monorepo,git-hooks,pre-commit-hook,pre-commit-hooks,subdirectory
Author: Egor Makarenko
Author-email: egormkn@yandex.ru
Requires-Python: >=3.8,<4.0
Classifier: Development Status :: 5 - Production/Stable
Classifier: Environment :: Console
Classifier: Intended Audience :: Developers
Classifier: License :: OSI Approved :: MIT License
Classifier: Programming Language :: Python :: 3
Classifier: Programming Language :: Python :: 3.8
Classifier: Programming Language :: Python :: 3.9
Classifier: Programming Language :: Python :: 3.10
Classifier: Programming Language :: Python :: 3.11
Classifier: Programming Language :: Python :: 3.12
Classifier: Topic :: Software Development
Classifier: Topic :: Software Development :: Version Control :: Git
Classifier: Topic :: Utilities
Project-URL: Repository, https://github.com/egormkn/run-in-subdirectory
